zy/__init__.py
zy/extract.py
zy-0.1.5.dist-info/METADATA
zy-0.1.5.dist-info/WHEEL
zy-0.1.5.dist-info/top_level.txt
zy-0.1.5.dist-info/RECORD
