Metadata-Version: 2.1
Name: zy
Version: 0.1.5
Summary: zy 子永的包
Home-page: https://gitee.com/only_zy/python_small_project
Author: zy-only
Author-email: ui829475@126.com
License: zy-wkr
Platform: UNKNOWN
Requires-Dist: numpy
Requires-Dist: xlwt
